pgclient-0.2.4.dist-info/pbr.json
pgclient-0.2.4.dist-info/metadata.json
pgclient-0.2.4.dist-info/METADATA
pgclient-0.2.4.dist-info/RECORD
pgclient-0.2.4.dist-info/DESCRIPTION.rst
pgclient-0.2.4.dist-info/top_level.txt
pgclient-0.2.4.dist-info/WHEEL
pgclient/tests.py
pgclient/exceptions.py
pgclient/client.py
pgclient/__init__.py
