Metadata-Version: 2.0
Name: pgclient
Version: 0.2.4
Summary: Yet another psycopg2 wrapper
Home-page: https://github.com/prawn-cake/pgclient
Author: Maksim Ekimovskii
Author-email: ekimovsky.maksim@gmail.com
License: MIT
Platform: UNKNOWN
Requires-Dist: psycopg2
